image_processing/__init__.py
image_processing/processing/__init__.py
image_processing/processing/combination.py
image_processing/processing/transformation.py
image_processing/utils/__init__.py
image_processing/utils/io.py
image_processing/utils/plot.py
package_processamento_imagem-0.0.5.dist-info/METADATA
package_processamento_imagem-0.0.5.dist-info/WHEEL
package_processamento_imagem-0.0.5.dist-info/top_level.txt
package_processamento_imagem-0.0.5.dist-info/RECORD
