Metadata-Version: 2.1
Name: package_processamento_imagem
Version: 0.0.5
Summary: biblioteca de processamento de imagens em Python que oferece uma ampla gama de ferramentas para a análise e manipulação de imagens
Home-page: https://github.com/gpfernando2024/image-processing-package
Author: Fernando Flavio F Ribeiro
Author-email: fernandoffribeirosistemas@gmail.com
Requires-Python: >=3.8
